zimmauth/__init__.py
zimmauth/core.py
zimmauth/local_conn.py
zimmauth/test_core.py
zimmauth-0.1.0.dist-info/LICENSE
zimmauth-0.1.0.dist-info/WHEEL
zimmauth-0.1.0.dist-info/METADATA
zimmauth-0.1.0.dist-info/RECORD
