Metadata-Version: 2.1
Name: zimmauth
Version: 0.1.0
Summary: Authentication encryption and storage
Author-email: Endre Márk Borza <endremborza@gmail.com>
Requires-Python: >=3.8
Requires-Dist: cryptography
Requires-Dist: branthebuilder[doc] ; extra == "doc"
Requires-Dist: toml ; extra == "env"
Requires-Dist: fabric ; extra == "ssh"
Requires-Dist: decorator ; extra == "ssh"
Requires-Dist: branthebuilder ; extra == "test"
Requires-Dist: mock-ssh-server ; extra == "test"
Requires-Dist: dvc[s3,ssh]>=3.1.0 ; extra == "test"
Requires-Dist: moto ; extra == "test"
Requires-Dist: aiobotocore ; extra == "test"
Requires-Dist: boto3 ; extra == "test"
Requires-Dist: fabric ; extra == "test"
Requires-Dist: toml ; extra == "test"
Requires-Dist: decorator ; extra == "test"
Project-URL: Homepage, https://github.com/endremborza/zimmauth
Provides-Extra: doc
Provides-Extra: env
Provides-Extra: ssh
Provides-Extra: test
